final_test01/__init__.py
final_test01/adaboost.py
final_test01/grad_boost.py
final_test01/knn.py
final_test01/logistic.py
final_test01/mlp.py
final_test01/perceptron.py
final_test01/random_forest.py
final_test01/sgd.py
final_test01/support_vector.py
final_test01/visualize.py
final_test01/xgboost.py
final_test_01-0.1.0.dist-info/LICENSE
final_test_01-0.1.0.dist-info/METADATA
final_test_01-0.1.0.dist-info/WHEEL
final_test_01-0.1.0.dist-info/top_level.txt
final_test_01-0.1.0.dist-info/RECORD
